[
    {
        "depart_date": "2024-11-27T22:05:00+03:00",
        "origin": "SKX",
        "destination": "MOW",
        "gate": "Kupi.com",
        "return_date": "",
        "found_at": "2024-11-25T23:27:18Z",
        "trip_class": 0,
        "value": 4514,
        "number_of_changes": 0,
        "duration": 90,
        "distance": 532,
        "show_to_affiliates": true,
        "actual": true,
        "flight_number": "6828",
        "link": "/search/SKX2711SVO1?t=SU17327451001732750500000090SKXSVO_2626a2f045f0b62f3d50a866c090a958_4514&search_date=25112024&expected_price_uuid=b5c72935-9ce1-4248-ac23-ed81212b9700&expected_price_source=share&expected_price_currency=rub&expected_price=4514",
        "origin_airport": "SKX",
        "destination_airport": "SVO",
        "departure_at": "2024-11-27T22:05:00+03:00",
        "airline": "FV",
        "price": 4514,
        "return_transfers": 0,
        "duration_to": 90,
        "duration_back": 0,
        "transfers": 0,
        "origin_airport_name": "Saransk Airport",
        "origin_city_code": "SKX",
        "origin_coordinates": {
            "lat": 54.166668,
            "lon": 45.166668
        },
        "origin_time_zone": "Europe/Moscow",
        "destination_airport_name": "Sheremetyevo International Airport",
        "destination_city_code": "MOW",
        "destination_coordinates": {
            "lat": 55.966324,
            "lon": 37.416573
        },
        "destination_time_zone": "Europe/Moscow"
    },
    {
        "depart_date": "2024-12-02T22:05:00+03:00",
        "origin": "SKX",
        "destination": "MOW",
        "gate": "Kupi.com",
        "return_date": "",
        "found_at": "2024-11-25T23:51:31Z",
        "trip_class": 0,
        "value": 4514,
        "number_of_changes": 0,
        "duration": 90,
        "distance": 532,
        "show_to_affiliates": true,
        "actual": true,
        "flight_number": "6828",
        "link": "/search/SKX0212SVO1?t=SU17331771001733182500000090SKXSVO_8a3b65bc36ea4aa442c96cba72060473_4514&search_date=25112024&expected_price_uuid=6089cf98-4449-45f9-9f64-b9a0122ee701&expected_price_source=share&expected_price_currency=rub&expected_price=4514",
        "origin_airport": "SKX",
        "destination_airport": "SVO",
        "departure_at": "2024-12-02T22:05:00+03:00",
        "airline": "FV",
        "price": 4514,
        "return_transfers": 0,
        "duration_to": 90,
        "duration_back": 0,
        "transfers": 0,
        "origin_airport_name": "Saransk Airport",
        "origin_city_code": "SKX",
        "origin_coordinates": {
            "lat": 54.166668,
            "lon": 45.166668
        },
        "origin_time_zone": "Europe/Moscow",
        "destination_airport_name": "Sheremetyevo International Airport",
        "destination_city_code": "MOW",
        "destination_coordinates": {
            "lat": 55.966324,
            "lon": 37.416573
        },
        "destination_time_zone": "Europe/Moscow"
    },
    {
        "depart_date": "2024-11-28T22:05:00+03:00",
        "origin": "SKX",
        "destination": "MOW",
        "gate": "Kupi.com",
        "return_date": "",
        "found_at": "2024-11-26T00:50:48Z",
        "trip_class": 0,
        "value": 4515,
        "number_of_changes": 0,
        "duration": 90,
        "distance": 532,
        "show_to_affiliates": true,
        "actual": true,
        "flight_number": "6828",
        "link": "/search/SKX2811SVO1?t=SU17328315001732836900000090SKXSVO_3ad939adb04670fdf7e17bb224684889_4514&search_date=26112024&expected_price_uuid=506d28ac-b331-4be6-99e0-0a0ec3013900&expected_price_source=share&expected_price_currency=rub&expected_price=4515",
        "origin_airport": "SKX",
        "destination_airport": "SVO",
        "departure_at": "2024-11-28T22:05:00+03:00",
        "airline": "FV",
        "price": 4515,
        "return_transfers": 0,
        "duration_to": 90,
        "duration_back": 0,
        "transfers": 0,
        "origin_airport_name": "Saransk Airport",
        "origin_city_code": "SKX",
        "origin_coordinates": {
            "lat": 54.166668,
            "lon": 45.166668
        },
        "origin_time_zone": "Europe/Moscow",
        "destination_airport_name": "Sheremetyevo International Airport",
        "destination_city_code": "MOW",
        "destination_coordinates": {
            "lat": 55.966324,
            "lon": 37.416573
        },
        "destination_time_zone": "Europe/Moscow"
    },
    {
        "depart_date": "2024-12-06T21:20:00+03:00",
        "origin": "SKX",
        "destination": "MOW",
        "gate": "Авиасейлс",
        "return_date": "",
        "found_at": "2024-11-25T20:03:01Z",
        "trip_class": 0,
        "value": 6205,
        "number_of_changes": 1,
        "duration": 265,
        "distance": 532,
        "show_to_affiliates": true,
        "actual": true,
        "flight_number": "650",
        "link": "/search/SKX0612SVO1?t=5N17335200001733535900000265SKXKZNSVO_192f54d9239a8a05ff76c729c4370637_6206&search_date=25112024&expected_price_uuid=5c8666de-190c-4dc0-8cc6-6fbcabfaa202&expected_price_source=share&expected_price_currency=rub&expected_price=6205",
        "origin_airport": "SKX",
        "destination_airport": "SVO",
        "departure_at": "2024-12-06T21:20:00+03:00",
        "airline": "RT",
        "price": 6205,
        "return_transfers": 0,
        "duration_to": 150,
        "duration_back": 0,
        "transfers": 1,
        "origin_airport_name": "Saransk Airport",
        "origin_city_code": "SKX",
        "origin_coordinates": {
            "lat": 54.166668,
            "lon": 45.166668
        },
        "origin_time_zone": "Europe/Moscow",
        "destination_airport_name": "Sheremetyevo International Airport",
        "destination_city_code": "MOW",
        "destination_coordinates": {
            "lat": 55.966324,
            "lon": 37.416573
        },
        "destination_time_zone": "Europe/Moscow"
    },
    {
        "depart_date": "2024-12-22T15:40:00+03:00",
        "origin": "SKX",
        "destination": "MOW",
        "gate": "OneTwoTrip",
        "return_date": "",
        "found_at": "2024-11-25T19:31:27Z",
        "trip_class": 0,
        "value": 6657,
        "number_of_changes": 1,
        "duration": 1970,
        "distance": 532,
        "show_to_affiliates": true,
        "actual": true,
        "flight_number": "650",
        "link": "/search/SKX2212SVO1?t=5N17348820001735000200001970SKXKZNSVO_b668e6da76e807429910b7a808eb45ed_6658&search_date=25112024&expected_price_uuid=6cb011ea-c594-488d-80a4-a52bbddb0b03&expected_price_source=share&expected_price_currency=rub&expected_price=6657",
        "origin_airport": "SKX",
        "destination_airport": "SVO",
        "departure_at": "2024-12-22T15:40:00+03:00",
        "airline": "RT",
        "price": 6657,
        "return_transfers": 0,
        "duration_to": 150,
        "duration_back": 0,
        "transfers": 1,
        "origin_airport_name": "Saransk Airport",
        "origin_city_code": "SKX",
        "origin_coordinates": {
            "lat": 54.166668,
            "lon": 45.166668
        },
        "origin_time_zone": "Europe/Moscow",
        "destination_airport_name": "Sheremetyevo International Airport",
        "destination_city_code": "MOW",
        "destination_coordinates": {
            "lat": 55.966324,
            "lon": 37.416573
        },
        "destination_time_zone": "Europe/Moscow"
    },
    {
        "depart_date": "2024-12-29T15:40:00+03:00",
        "origin": "SKX",
        "destination": "MOW",
        "gate": "OneTwoTrip",
        "return_date": "",
        "found_at": "2024-11-25T20:18:12Z",
        "trip_class": 0,
        "value": 6657,
        "number_of_changes": 1,
        "duration": 515,
        "distance": 532,
        "show_to_affiliates": true,
        "actual": true,
        "flight_number": "650",
        "link": "/search/SKX2912SVO1?t=5N17354868001735517700000515SKXKZNSVO_bc434569c8eded1f81bd8261f3e06eb9_6658&search_date=25112024&expected_price_uuid=2e0cff16-a5f2-4391-9259-561b61877303&expected_price_source=share&expected_price_currency=rub&expected_price=6657",
        "origin_airport": "SKX",
        "destination_airport": "SVO",
        "departure_at": "2024-12-29T15:40:00+03:00",
        "airline": "RT",
        "price": 6657,
        "return_transfers": 0,
        "duration_to": 150,
        "duration_back": 0,
        "transfers": 1,
        "origin_airport_name": "Saransk Airport",
        "origin_city_code": "SKX",
        "origin_coordinates": {
            "lat": 54.166668,
            "lon": 45.166668
        },
        "origin_time_zone": "Europe/Moscow",
        "destination_airport_name": "Sheremetyevo International Airport",
        "destination_city_code": "MOW",
        "destination_coordinates": {
            "lat": 55.966324,
            "lon": 37.416573
        },
        "destination_time_zone": "Europe/Moscow"
    },
    {
        "depart_date": "2024-12-20T21:20:00+03:00",
        "origin": "SKX",
        "destination": "MOW",
        "gate": "Kupi.com",
        "return_date": "",
        "found_at": "2024-11-25T23:51:26Z",
        "trip_class": 0,
        "value": 6670,
        "number_of_changes": 1,
        "duration": 1530,
        "distance": 532,
        "show_to_affiliates": true,
        "actual": true,
        "flight_number": "650",
        "link": "/search/SKX2012SVO1?t=DP17347296001734821400001530SKXKZNSVO_254d42a6b58f9682d203437599d49252_6670&search_date=25112024&expected_price_uuid=d140ecf9-a691-4f06-b191-a80dc6e13903&expected_price_source=share&expected_price_currency=rub&expected_price=6670",
        "origin_airport": "SKX",
        "destination_airport": "SVO",
        "departure_at": "2024-12-20T21:20:00+03:00",
        "airline": "RT",
        "price": 6670,
        "return_transfers": 0,
        "duration_to": 160,
        "duration_back": 0,
        "transfers": 1,
        "origin_airport_name": "Saransk Airport",
        "origin_city_code": "SKX",
        "origin_coordinates": {
            "lat": 54.166668,
            "lon": 45.166668
        },
        "origin_time_zone": "Europe/Moscow",
        "destination_airport_name": "Sheremetyevo International Airport",
        "destination_city_code": "MOW",
        "destination_coordinates": {
            "lat": 55.966324,
            "lon": 37.416573
        },
        "destination_time_zone": "Europe/Moscow"
    },
    {
        "depart_date": "2024-12-01T15:40:00+03:00",
        "origin": "SKX",
        "destination": "MOW",
        "gate": "Авиасейлс",
        "return_date": "",
        "found_at": "2024-11-25T20:20:45Z",
        "trip_class": 0,
        "value": 6776,
        "number_of_changes": 1,
        "duration": 1340,
        "distance": 532,
        "show_to_affiliates": true,
        "actual": true,
        "flight_number": "650",
        "link": "/search/SKX0112SVO1?t=N417330676001733148000001340SKXKZNSVO_3ac570fb06f5e8e2eebabdb612e85b70_6777&search_date=25112024&expected_price_uuid=6c5f38d1-a0c1-4e5e-9e1e-0de6ea46a603&expected_price_source=share&expected_price_currency=rub&expected_price=6776",
        "origin_airport": "SKX",
        "destination_airport": "SVO",
        "departure_at": "2024-12-01T15:40:00+03:00",
        "airline": "RT",
        "price": 6776,
        "return_transfers": 0,
        "duration_to": 160,
        "duration_back": 0,
        "transfers": 1,
        "origin_airport_name": "Saransk Airport",
        "origin_city_code": "SKX",
        "origin_coordinates": {
            "lat": 54.166668,
            "lon": 45.166668
        },
        "origin_time_zone": "Europe/Moscow",
        "destination_airport_name": "Sheremetyevo International Airport",
        "destination_city_code": "MOW",
        "destination_coordinates": {
            "lat": 55.966324,
            "lon": 37.416573
        },
        "destination_time_zone": "Europe/Moscow"
    },
    {
        "depart_date": "2024-12-13T21:20:00+03:00",
        "origin": "SKX",
        "destination": "MOW",
        "gate": "Авиасейлс",
        "return_date": "",
        "found_at": "2024-11-25T19:26:42Z",
        "trip_class": 0,
        "value": 6868,
        "number_of_changes": 1,
        "duration": 265,
        "distance": 532,
        "show_to_affiliates": true,
        "actual": true,
        "flight_number": "650",
        "link": "/search/SKX1312SVO1?t=5N17341248001734140700000265SKXKZNSVO_1c9ed0a6139e47f4bed1d6e16121f4b1_6869&search_date=25112024&expected_price_uuid=5b70c58e-e6e7-4dd7-81cb-da273c7af800&expected_price_source=share&expected_price_currency=rub&expected_price=6868",
        "origin_airport": "SKX",
        "destination_airport": "SVO",
        "departure_at": "2024-12-13T21:20:00+03:00",
        "airline": "RT",
        "price": 6868,
        "return_transfers": 0,
        "duration_to": 150,
        "duration_back": 0,
        "transfers": 1,
        "origin_airport_name": "Saransk Airport",
        "origin_city_code": "SKX",
        "origin_coordinates": {
            "lat": 54.166668,
            "lon": 45.166668
        },
        "origin_time_zone": "Europe/Moscow",
        "destination_airport_name": "Sheremetyevo International Airport",
        "destination_city_code": "MOW",
        "destination_coordinates": {
            "lat": 55.966324,
            "lon": 37.416573
        },
        "destination_time_zone": "Europe/Moscow"
    },
    {
        "depart_date": "2024-11-29T21:20:00+03:00",
        "origin": "SKX",
        "destination": "MOW",
        "gate": "Авиасейлс",
        "return_date": "",
        "found_at": "2024-11-26T00:50:32Z",
        "trip_class": 0,
        "value": 6871,
        "number_of_changes": 1,
        "duration": 265,
        "distance": 532,
        "show_to_affiliates": true,
        "actual": true,
        "flight_number": "650",
        "link": "/search/SKX2911SVO1?t=5N17329152001732931100000265SKXKZNSVO_41ac34662f3fd1455cd7b2c5b8ce08c1_6869&search_date=26112024&expected_price_uuid=366de40b-2644-4cc5-afaf-dd957317cb03&expected_price_source=share&expected_price_currency=rub&expected_price=6871",
        "origin_airport": "SKX",
        "destination_airport": "SVO",
        "departure_at": "2024-11-29T21:20:00+03:00",
        "airline": "RT",
        "price": 6871,
        "return_transfers": 0,
        "duration_to": 150,
        "duration_back": 0,
        "transfers": 1,
        "origin_airport_name": "Saransk Airport",
        "origin_city_code": "SKX",
        "origin_coordinates": {
            "lat": 54.166668,
            "lon": 45.166668
        },
        "origin_time_zone": "Europe/Moscow",
        "destination_airport_name": "Sheremetyevo International Airport",
        "destination_city_code": "MOW",
        "destination_coordinates": {
            "lat": 55.966324,
            "lon": 37.416573
        },
        "destination_time_zone": "Europe/Moscow"
    },
    {
        "depart_date": "2024-12-27T21:20:00+03:00",
        "origin": "SKX",
        "destination": "MOW",
        "gate": "Kupi.com",
        "return_date": "",
        "found_at": "2024-11-25T18:04:41Z",
        "trip_class": 0,
        "value": 6981,
        "number_of_changes": 1,
        "duration": 3055,
        "distance": 532,
        "show_to_affiliates": true,
        "actual": true,
        "flight_number": "650",
        "link": "/search/SKX2712SVO1?t=5N17353344001735517700003055SKXKZNSVO_353be8d21dd1c83f3a5432da4ac676fb_6981&search_date=25112024&expected_price_uuid=37c1195b-a8f5-4113-9896-0c178353bd01&expected_price_source=share&expected_price_currency=rub&expected_price=6981",
        "origin_airport": "SKX",
        "destination_airport": "SVO",
        "departure_at": "2024-12-27T21:20:00+03:00",
        "airline": "RT",
        "price": 6981,
        "return_transfers": 0,
        "duration_to": 150,
        "duration_back": 0,
        "transfers": 1,
        "origin_airport_name": "Saransk Airport",
        "origin_city_code": "SKX",
        "origin_coordinates": {
            "lat": 54.166668,
            "lon": 45.166668
        },
        "origin_time_zone": "Europe/Moscow",
        "destination_airport_name": "Sheremetyevo International Airport",
        "destination_city_code": "MOW",
        "destination_coordinates": {
            "lat": 55.966324,
            "lon": 37.416573
        },
        "destination_time_zone": "Europe/Moscow"
    },
    {
        "depart_date": "2024-12-12T14:05:00+03:00",
        "origin": "SKX",
        "destination": "MOW",
        "gate": "Авиасейлс",
        "return_date": "",
        "found_at": "2024-11-25T12:02:00Z",
        "trip_class": 0,
        "value": 7023,
        "number_of_changes": 1,
        "duration": 550,
        "distance": 532,
        "show_to_affiliates": true,
        "actual": true,
        "flight_number": "6009",
        "link": "/search/SKX1212SVO1?t=A417340123001734045300000550SKXLEDSVO_193c03cfaee522766172b769e1f8c3b1_7028&search_date=25112024&expected_price_uuid=bcf8536a-2742-4dad-97ee-28c8fd17bf00&expected_price_source=share&expected_price_currency=rub&expected_price=7023",
        "origin_airport": "SKX",
        "destination_airport": "SVO",
        "departure_at": "2024-12-12T14:05:00+03:00",
        "airline": "A4",
        "price": 7023,
        "return_transfers": 0,
        "duration_to": 240,
        "duration_back": 0,
        "transfers": 1,
        "origin_airport_name": "Saransk Airport",
        "origin_city_code": "SKX",
        "origin_coordinates": {
            "lat": 54.166668,
            "lon": 45.166668
        },
        "origin_time_zone": "Europe/Moscow",
        "destination_airport_name": "Sheremetyevo International Airport",
        "destination_city_code": "MOW",
        "destination_coordinates": {
            "lat": 55.966324,
            "lon": 37.416573
        },
        "destination_time_zone": "Europe/Moscow"
    },
    {
        "depart_date": "2024-11-25T22:05:00+03:00",
        "origin": "SKX",
        "destination": "MOW",
        "gate": "Kupi.com",
        "return_date": "",
        "found_at": "2024-11-25T14:31:39Z",
        "trip_class": 0,
        "value": 7071,
        "number_of_changes": 0,
        "duration": 90,
        "distance": 532,
        "show_to_affiliates": true,
        "actual": true,
        "flight_number": "6828",
        "link": "/search/SKX2511SVO1?t=SU17325723001732577700000090SKXSVO_01b0393a344e358ae8feab148185f862_7077&search_date=25112024&expected_price_uuid=ecabe98f-69a2-47b2-bfe4-7e6930959102&expected_price_source=share&expected_price_currency=rub&expected_price=7071",
        "origin_airport": "SKX",
        "destination_airport": "SVO",
        "departure_at": "2024-11-25T22:05:00+03:00",
        "airline": "FV",
        "price": 7071,
        "return_transfers": 0,
        "duration_to": 90,
        "duration_back": 0,
        "transfers": 0,
        "origin_airport_name": "Saransk Airport",
        "origin_city_code": "SKX",
        "origin_coordinates": {
            "lat": 54.166668,
            "lon": 45.166668
        },
        "origin_time_zone": "Europe/Moscow",
        "destination_airport_name": "Sheremetyevo International Airport",
        "destination_city_code": "MOW",
        "destination_coordinates": {
            "lat": 55.966324,
            "lon": 37.416573
        },
        "destination_time_zone": "Europe/Moscow"
    },
    {
        "depart_date": "2024-12-05T22:05:00+03:00",
        "origin": "SKX",
        "destination": "MOW",
        "gate": "Kupi.com",
        "return_date": "",
        "found_at": "2024-11-25T21:26:08Z",
        "trip_class": 0,
        "value": 7077,
        "number_of_changes": 0,
        "duration": 90,
        "distance": 532,
        "show_to_affiliates": true,
        "actual": true,
        "flight_number": "6828",
        "link": "/search/SKX0512SVO1?t=SU17334363001733441700000090SKXSVO_900ed68143ed1c137dc705c1312253e4_7077&search_date=25112024&expected_price_uuid=ac6ef072-7172-4193-9f43-27cf933cc103&expected_price_source=share&expected_price_currency=rub&expected_price=7077",
        "origin_airport": "SKX",
        "destination_airport": "SVO",
        "departure_at": "2024-12-05T22:05:00+03:00",
        "airline": "FV",
        "price": 7077,
        "return_transfers": 0,
        "duration_to": 90,
        "duration_back": 0,
        "transfers": 0,
        "origin_airport_name": "Saransk Airport",
        "origin_city_code": "SKX",
        "origin_coordinates": {
            "lat": 54.166668,
            "lon": 45.166668
        },
        "origin_time_zone": "Europe/Moscow",
        "destination_airport_name": "Sheremetyevo International Airport",
        "destination_city_code": "MOW",
        "destination_coordinates": {
            "lat": 55.966324,
            "lon": 37.416573
        },
        "destination_time_zone": "Europe/Moscow"
    },
    {
        "depart_date": "2024-12-15T15:40:00+03:00",
        "origin": "SKX",
        "destination": "MOW",
        "gate": "MEGO.travel",
        "return_date": "",
        "found_at": "2024-11-25T19:50:11Z",
        "trip_class": 0,
        "value": 7089,
        "number_of_changes": 1,
        "duration": 1290,
        "distance": 532,
        "show_to_affiliates": true,
        "actual": true,
        "flight_number": "650",
        "link": "/search/SKX1512SVO1?t=DP17342772001734354600001290SKXKZNSVO_13f11f86db7d724b91bc4fee75b92e9e_7090&search_date=25112024&expected_price_uuid=2ba77c73-b26c-4ebe-bdbb-2467fbeab902&expected_price_source=share&expected_price_currency=rub&expected_price=7089",
        "origin_airport": "SKX",
        "destination_airport": "SVO",
        "departure_at": "2024-12-15T15:40:00+03:00",
        "airline": "RT",
        "price": 7089,
        "return_transfers": 0,
        "duration_to": 165,
        "duration_back": 0,
        "transfers": 1,
        "origin_airport_name": "Saransk Airport",
        "origin_city_code": "SKX",
        "origin_coordinates": {
            "lat": 54.166668,
            "lon": 45.166668
        },
        "origin_time_zone": "Europe/Moscow",
        "destination_airport_name": "Sheremetyevo International Airport",
        "destination_city_code": "MOW",
        "destination_coordinates": {
            "lat": 55.966324,
            "lon": 37.416573
        },
        "destination_time_zone": "Europe/Moscow"
    },
    {
        "depart_date": "2024-11-26T00:30:00+03:00",
        "origin": "SKX",
        "destination": "MOW",
        "gate": "Kupi.com",
        "return_date": "",
        "found_at": "2024-11-25T19:50:14Z",
        "trip_class": 0,
        "value": 7160,
        "number_of_changes": 1,
        "duration": 2815,
        "distance": 532,
        "show_to_affiliates": true,
        "actual": true,
        "flight_number": "6010",
        "link": "/search/SKX2611SVO1?t=DP17325810001732749900002815SKXMRVSVO_355206f14370d3d37b7620fe4b549e7e_7161&search_date=25112024&expected_price_uuid=1c2d27ad-dae7-4a84-9369-0621c5ef0501&expected_price_source=share&expected_price_currency=rub&expected_price=7160",
        "origin_airport": "SKX",
        "destination_airport": "SVO",
        "departure_at": "2024-11-26T00:30:00+03:00",
        "airline": "A4",
        "price": 7160,
        "return_transfers": 0,
        "duration_to": 350,
        "duration_back": 0,
        "transfers": 1,
        "origin_airport_name": "Saransk Airport",
        "origin_city_code": "SKX",
        "origin_coordinates": {
            "lat": 54.166668,
            "lon": 45.166668
        },
        "origin_time_zone": "Europe/Moscow",
        "destination_airport_name": "Sheremetyevo International Airport",
        "destination_city_code": "MOW",
        "destination_coordinates": {
            "lat": 55.966324,
            "lon": 37.416573
        },
        "destination_time_zone": "Europe/Moscow"
    },
    {
        "depart_date": "2024-12-08T15:40:00+03:00",
        "origin": "SKX",
        "destination": "MOW",
        "gate": "Авиасейлс",
        "return_date": "",
        "found_at": "2024-11-25T20:54:59Z",
        "trip_class": 0,
        "value": 7311,
        "number_of_changes": 1,
        "duration": 1970,
        "distance": 532,
        "show_to_affiliates": true,
        "actual": true,
        "flight_number": "650",
        "link": "/search/SKX0812SVO1?t=5N17336724001733790600001970SKXKZNSVO_16494151f8126a3342eab1e113c9770e_7311&search_date=25112024&expected_price_uuid=e956961d-d87f-40d9-b77f-bb259c44de03&expected_price_source=share&expected_price_currency=rub&expected_price=7311",
        "origin_airport": "SKX",
        "destination_airport": "SVO",
        "departure_at": "2024-12-08T15:40:00+03:00",
        "airline": "RT",
        "price": 7311,
        "return_transfers": 0,
        "duration_to": 150,
        "duration_back": 0,
        "transfers": 1,
        "origin_airport_name": "Saransk Airport",
        "origin_city_code": "SKX",
        "origin_coordinates": {
            "lat": 54.166668,
            "lon": 45.166668
        },
        "origin_time_zone": "Europe/Moscow",
        "destination_airport_name": "Sheremetyevo International Airport",
        "destination_city_code": "MOW",
        "destination_coordinates": {
            "lat": 55.966324,
            "lon": 37.416573
        },
        "destination_time_zone": "Europe/Moscow"
    },
    {
        "depart_date": "2024-12-16T21:10:00+03:00",
        "origin": "SKX",
        "destination": "MOW",
        "gate": "Авиасейлс",
        "return_date": "",
        "found_at": "2024-11-25T06:58:01Z",
        "trip_class": 0,
        "value": 7494,
        "number_of_changes": 1,
        "duration": 1605,
        "distance": 532,
        "show_to_affiliates": true,
        "actual": true,
        "flight_number": "6009",
        "link": "/search/SKX1612SVO1?t=A417343834001734479700001605SKXLEDSVO_f3a96b88bdfef0c47b44a1070d2058ae_7474&search_date=25112024&expected_price_uuid=c3b2c53a-cf1d-4c5d-b563-fc4fb581df03&expected_price_source=share&expected_price_currency=rub&expected_price=7494",
        "origin_airport": "SKX",
        "destination_airport": "SVO",
        "departure_at": "2024-12-16T21:10:00+03:00",
        "airline": "A4",
        "price": 7494,
        "return_transfers": 0,
        "duration_to": 225,
        "duration_back": 0,
        "transfers": 1,
        "origin_airport_name": "Saransk Airport",
        "origin_city_code": "SKX",
        "origin_coordinates": {
            "lat": 54.166668,
            "lon": 45.166668
        },
        "origin_time_zone": "Europe/Moscow",
        "destination_airport_name": "Sheremetyevo International Airport",
        "destination_city_code": "MOW",
        "destination_coordinates": {
            "lat": 55.966324,
            "lon": 37.416573
        },
        "destination_time_zone": "Europe/Moscow"
    },
    {
        "depart_date": "2024-12-03T03:35:00+03:00",
        "origin": "SKX",
        "destination": "MOW",
        "gate": "Aviakassa",
        "return_date": "",
        "found_at": "2024-11-25T23:04:01Z",
        "trip_class": 0,
        "value": 7728,
        "number_of_changes": 1,
        "duration": 1170,
        "distance": 532,
        "show_to_affiliates": true,
        "actual": true,
        "flight_number": "6010",
        "link": "/search/SKX0312SVO1?t=SU17331969001733267100001170SKXMRVSVO_87b31fe07ba8a29d66d2f523725eeaa9_7728&search_date=25112024&expected_price_uuid=7bcb6b49-c746-4ab7-a7b3-e2a506ab8603&expected_price_source=share&expected_price_currency=rub&expected_price=7728",
        "origin_airport": "SKX",
        "destination_airport": "SVO",
        "departure_at": "2024-12-03T03:35:00+03:00",
        "airline": "A4",
        "price": 7728,
        "return_transfers": 0,
        "duration_to": 335,
        "duration_back": 0,
        "transfers": 1,
        "origin_airport_name": "Saransk Airport",
        "origin_city_code": "SKX",
        "origin_coordinates": {
            "lat": 54.166668,
            "lon": 45.166668
        },
        "origin_time_zone": "Europe/Moscow",
        "destination_airport_name": "Sheremetyevo International Airport",
        "destination_city_code": "MOW",
        "destination_coordinates": {
            "lat": 55.966324,
            "lon": 37.416573
        },
        "destination_time_zone": "Europe/Moscow"
    },
    {
        "depart_date": "2024-12-19T14:05:00+03:00",
        "origin": "SKX",
        "destination": "MOW",
        "gate": "Авиасейлс",
        "return_date": "",
        "found_at": "2024-11-25T03:51:52Z",
        "trip_class": 0,
        "value": 7791,
        "number_of_changes": 1,
        "duration": 550,
        "distance": 532,
        "show_to_affiliates": true,
        "actual": true,
        "flight_number": "6009",
        "link": "/search/SKX1912SVO1?t=A417346171001734650100000550SKXLEDSVO_19a03720253debfbb4faefe027405134_7764&search_date=25112024&expected_price_uuid=fbdc0717-00a1-4df2-8531-45c945339702&expected_price_source=share&expected_price_currency=rub&expected_price=7791",
        "origin_airport": "SKX",
        "destination_airport": "SVO",
        "departure_at": "2024-12-19T14:05:00+03:00",
        "airline": "A4",
        "price": 7791,
        "return_transfers": 0,
        "duration_to": 240,
        "duration_back": 0,
        "transfers": 1,
        "origin_airport_name": "Saransk Airport",
        "origin_city_code": "SKX",
        "origin_coordinates": {
            "lat": 54.166668,
            "lon": 45.166668
        },
        "origin_time_zone": "Europe/Moscow",
        "destination_airport_name": "Sheremetyevo International Airport",
        "destination_city_code": "MOW",
        "destination_coordinates": {
            "lat": 55.966324,
            "lon": 37.416573
        },
        "destination_time_zone": "Europe/Moscow"
    },
    {
        "depart_date": "2024-12-11T15:50:00+03:00",
        "origin": "SKX",
        "destination": "MOW",
        "gate": "OneTwoTrip",
        "return_date": "",
        "found_at": "2024-11-25T20:17:56Z",
        "trip_class": 0,
        "value": 8709,
        "number_of_changes": 1,
        "duration": 1795,
        "distance": 532,
        "show_to_affiliates": true,
        "actual": true,
        "flight_number": "5009",
        "link": "/search/SKX1112SVO1?t=A417339322001734039900001795SKXLEDSVO_4ca55664a4f0ad401e5d9eaf5f3db358_8710&search_date=25112024&expected_price_uuid=b76e465a-5e75-46d9-a74b-7f0ea6853e03&expected_price_source=share&expected_price_currency=rub&expected_price=8709",
        "origin_airport": "SKX",
        "destination_airport": "SVO",
        "departure_at": "2024-12-11T15:50:00+03:00",
        "airline": "A4",
        "price": 8709,
        "return_transfers": 0,
        "duration_to": 235,
        "duration_back": 0,
        "transfers": 1,
        "origin_airport_name": "Saransk Airport",
        "origin_city_code": "SKX",
        "origin_coordinates": {
            "lat": 54.166668,
            "lon": 45.166668
        },
        "origin_time_zone": "Europe/Moscow",
        "destination_airport_name": "Sheremetyevo International Airport",
        "destination_city_code": "MOW",
        "destination_coordinates": {
            "lat": 55.966324,
            "lon": 37.416573
        },
        "destination_time_zone": "Europe/Moscow"
    },
    {
        "depart_date": "2024-12-04T15:50:00+03:00",
        "origin": "SKX",
        "destination": "MOW",
        "gate": "Авиасейлс",
        "return_date": "",
        "found_at": "2024-11-25T23:15:05Z",
        "trip_class": 0,
        "value": 9083,
        "number_of_changes": 1,
        "duration": 1670,
        "distance": 532,
        "show_to_affiliates": true,
        "actual": true,
        "flight_number": "5009",
        "link": "/search/SKX0412SVO1?t=A417333274001733427600001670SKXLEDSVO_433f70733304519f3b58f63140ba91c3_9083&search_date=25112024&expected_price_uuid=d4f8a867-6bde-4022-8922-61f2f264e100&expected_price_source=share&expected_price_currency=rub&expected_price=9083",
        "origin_airport": "SKX",
        "destination_airport": "SVO",
        "departure_at": "2024-12-04T15:50:00+03:00",
        "airline": "A4",
        "price": 9083,
        "return_transfers": 0,
        "duration_to": 225,
        "duration_back": 0,
        "transfers": 1,
        "origin_airport_name": "Saransk Airport",
        "origin_city_code": "SKX",
        "origin_coordinates": {
            "lat": 54.166668,
            "lon": 45.166668
        },
        "origin_time_zone": "Europe/Moscow",
        "destination_airport_name": "Sheremetyevo International Airport",
        "destination_city_code": "MOW",
        "destination_coordinates": {
            "lat": 55.966324,
            "lon": 37.416573
        },
        "destination_time_zone": "Europe/Moscow"
    },
    {
        "depart_date": "2024-12-18T15:50:00+03:00",
        "origin": "SKX",
        "destination": "MOW",
        "gate": "Авиасейлс",
        "return_date": "",
        "found_at": "2024-11-25T07:22:10Z",
        "trip_class": 0,
        "value": 9436,
        "number_of_changes": 1,
        "duration": 1885,
        "distance": 532,
        "show_to_affiliates": true,
        "actual": true,
        "flight_number": "5009",
        "link": "/search/SKX1812SVO1?t=A417345370001734650100001885SKXLEDSVO_4347c97270175429c2c1f5764fa3d974_9410&search_date=25112024&expected_price_uuid=d8b24970-5880-48af-8222-3ed65950f502&expected_price_source=share&expected_price_currency=rub&expected_price=9436",
        "origin_airport": "SKX",
        "destination_airport": "SVO",
        "departure_at": "2024-12-18T15:50:00+03:00",
        "airline": "A4",
        "price": 9436,
        "return_transfers": 0,
        "duration_to": 240,
        "duration_back": 0,
        "transfers": 1,
        "origin_airport_name": "Saransk Airport",
        "origin_city_code": "SKX",
        "origin_coordinates": {
            "lat": 54.166668,
            "lon": 45.166668
        },
        "origin_time_zone": "Europe/Moscow",
        "destination_airport_name": "Sheremetyevo International Airport",
        "destination_city_code": "MOW",
        "destination_coordinates": {
            "lat": 55.966324,
            "lon": 37.416573
        },
        "destination_time_zone": "Europe/Moscow"
    },
    {
        "depart_date": "2024-12-10T03:35:00+03:00",
        "origin": "SKX",
        "destination": "MOW",
        "gate": "Kupi.com",
        "return_date": "",
        "found_at": "2024-11-25T13:19:34Z",
        "trip_class": 0,
        "value": 9553,
        "number_of_changes": 1,
        "duration": 815,
        "distance": 532,
        "show_to_affiliates": true,
        "actual": true,
        "flight_number": "6010",
        "link": "/search/SKX1012SVO1?t=SU17338017001733850600000815SKXMRVSVO_5f28264a7401b8198e1dcfe61d4cda86_9554&search_date=25112024&expected_price_uuid=c46e5f84-0237-4114-a77a-d5f2cdab7401&expected_price_source=share&expected_price_currency=rub&expected_price=9553",
        "origin_airport": "SKX",
        "destination_airport": "SVO",
        "departure_at": "2024-12-10T03:35:00+03:00",
        "airline": "A4",
        "price": 9553,
        "return_transfers": 0,
        "duration_to": 345,
        "duration_back": 0,
        "transfers": 1,
        "origin_airport_name": "Saransk Airport",
        "origin_city_code": "SKX",
        "origin_coordinates": {
            "lat": 54.166668,
            "lon": 45.166668
        },
        "origin_time_zone": "Europe/Moscow",
        "destination_airport_name": "Sheremetyevo International Airport",
        "destination_city_code": "MOW",
        "destination_coordinates": {
            "lat": 55.966324,
            "lon": 37.416573
        },
        "destination_time_zone": "Europe/Moscow"
    },
    {
        "depart_date": "2024-12-25T22:05:00+03:00",
        "origin": "SKX",
        "destination": "MOW",
        "gate": "Kupi.com",
        "return_date": "",
        "found_at": "2024-11-21T19:26:45Z",
        "trip_class": 0,
        "value": 9622,
        "number_of_changes": 0,
        "duration": 90,
        "distance": 532,
        "show_to_affiliates": true,
        "actual": true,
        "flight_number": "6828",
        "link": "/search/SKX2512SVO1?t=SU17351643001735169700000090SKXSVO_753e90992ae489acbbf6af402a0daafb_9624&search_date=21112024&expected_price_uuid=7e0f0056-3326-4f18-8fb2-dd8c8d138b01&expected_price_source=share&expected_price_currency=rub&expected_price=9622",
        "origin_airport": "SKX",
        "destination_airport": "SVO",
        "departure_at": "2024-12-25T22:05:00+03:00",
        "airline": "FV",
        "price": 9622,
        "return_transfers": 0,
        "duration_to": 90,
        "duration_back": 0,
        "transfers": 0,
        "origin_airport_name": "Saransk Airport",
        "origin_city_code": "SKX",
        "origin_coordinates": {
            "lat": 54.166668,
            "lon": 45.166668
        },
        "origin_time_zone": "Europe/Moscow",
        "destination_airport_name": "Sheremetyevo International Airport",
        "destination_city_code": "MOW",
        "destination_coordinates": {
            "lat": 55.966324,
            "lon": 37.416573
        },
        "destination_time_zone": "Europe/Moscow"
    },
    {
        "depart_date": "2024-12-23T22:05:00+03:00",
        "origin": "SKX",
        "destination": "MOW",
        "gate": "Kupi.com",
        "return_date": "",
        "found_at": "2024-11-25T18:00:13Z",
        "trip_class": 0,
        "value": 9623,
        "number_of_changes": 0,
        "duration": 90,
        "distance": 532,
        "show_to_affiliates": true,
        "actual": true,
        "flight_number": "6828",
        "link": "/search/SKX2312SVO1?t=SU17349915001734996900000090SKXSVO_bab86bd8c65d8936b006a672ec74d22a_9624&search_date=25112024&expected_price_uuid=f307e3bb-010b-41a1-8b29-66e3090c4802&expected_price_source=share&expected_price_currency=rub&expected_price=9623",
        "origin_airport": "SKX",
        "destination_airport": "SVO",
        "departure_at": "2024-12-23T22:05:00+03:00",
        "airline": "FV",
        "price": 9623,
        "return_transfers": 0,
        "duration_to": 90,
        "duration_back": 0,
        "transfers": 0,
        "origin_airport_name": "Saransk Airport",
        "origin_city_code": "SKX",
        "origin_coordinates": {
            "lat": 54.166668,
            "lon": 45.166668
        },
        "origin_time_zone": "Europe/Moscow",
        "destination_airport_name": "Sheremetyevo International Airport",
        "destination_city_code": "MOW",
        "destination_coordinates": {
            "lat": 55.966324,
            "lon": 37.416573
        },
        "destination_time_zone": "Europe/Moscow"
    },
    {
        "depart_date": "2024-12-30T22:05:00+03:00",
        "origin": "SKX",
        "destination": "MOW",
        "gate": "Kupi.com",
        "return_date": "",
        "found_at": "2024-11-26T01:40:59Z",
        "trip_class": 0,
        "value": 9624,
        "number_of_changes": 0,
        "duration": 90,
        "distance": 532,
        "show_to_affiliates": true,
        "actual": true,
        "flight_number": "6828",
        "link": "/search/SKX3012SVO1?t=SU17355963001735601700000090SKXSVO_b565ff6b8ae069fa2da86bc84d859a71_9624&search_date=26112024&expected_price_uuid=16b66e2d-6546-4363-a6ce-0595ce025000&expected_price_source=share&expected_price_currency=rub&expected_price=9624",
        "origin_airport": "SKX",
        "destination_airport": "SVO",
        "departure_at": "2024-12-30T22:05:00+03:00",
        "airline": "FV",
        "price": 9624,
        "return_transfers": 0,
        "duration_to": 90,
        "duration_back": 0,
        "transfers": 0,
        "origin_airport_name": "Saransk Airport",
        "origin_city_code": "SKX",
        "origin_coordinates": {
            "lat": 54.166668,
            "lon": 45.166668
        },
        "origin_time_zone": "Europe/Moscow",
        "destination_airport_name": "Sheremetyevo International Airport",
        "destination_city_code": "MOW",
        "destination_coordinates": {
            "lat": 55.966324,
            "lon": 37.416573
        },
        "destination_time_zone": "Europe/Moscow"
    },
    {
        "depart_date": "2024-12-26T22:05:00+03:00",
        "origin": "SKX",
        "destination": "MOW",
        "gate": "Kupi.com",
        "return_date": "",
        "found_at": "2024-11-23T17:00:03Z",
        "trip_class": 0,
        "value": 9624,
        "number_of_changes": 0,
        "duration": 90,
        "distance": 532,
        "show_to_affiliates": true,
        "actual": true,
        "flight_number": "6828",
        "link": "/search/SKX2612SVO1?t=SU17352507001735256100000090SKXSVO_0c43bdd7edc47eea937290ff33c2a843_9624&search_date=23112024&expected_price_uuid=8688a685-b8e6-49ae-84c6-a2dc03dae901&expected_price_source=share&expected_price_currency=rub&expected_price=9624",
        "origin_airport": "SKX",
        "destination_airport": "SVO",
        "departure_at": "2024-12-26T22:05:00+03:00",
        "airline": "FV",
        "price": 9624,
        "return_transfers": 0,
        "duration_to": 90,
        "duration_back": 0,
        "transfers": 0,
        "origin_airport_name": "Saransk Airport",
        "origin_city_code": "SKX",
        "origin_coordinates": {
            "lat": 54.166668,
            "lon": 45.166668
        },
        "origin_time_zone": "Europe/Moscow",
        "destination_airport_name": "Sheremetyevo International Airport",
        "destination_city_code": "MOW",
        "destination_coordinates": {
            "lat": 55.966324,
            "lon": 37.416573
        },
        "destination_time_zone": "Europe/Moscow"
    },
    {
        "depart_date": "2024-12-09T22:05:00+03:00",
        "origin": "SKX",
        "destination": "MOW",
        "gate": "Kupi.com",
        "return_date": "",
        "found_at": "2024-11-25T21:26:35Z",
        "trip_class": 0,
        "value": 9624,
        "number_of_changes": 0,
        "duration": 90,
        "distance": 532,
        "show_to_affiliates": true,
        "actual": true,
        "flight_number": "6828",
        "link": "/search/SKX0912SVO1?t=SU17337819001733787300000090SKXSVO_bfc33fdae1e84240d5776a28e2d16379_9624&search_date=25112024&expected_price_uuid=381ae5d1-c559-4243-9ff2-6a58fec07200&expected_price_source=share&expected_price_currency=rub&expected_price=9624",
        "origin_airport": "SKX",
        "destination_airport": "SVO",
        "departure_at": "2024-12-09T22:05:00+03:00",
        "airline": "FV",
        "price": 9624,
        "return_transfers": 0,
        "duration_to": 90,
        "duration_back": 0,
        "transfers": 0,
        "origin_airport_name": "Saransk Airport",
        "origin_city_code": "SKX",
        "origin_coordinates": {
            "lat": 54.166668,
            "lon": 45.166668
        },
        "origin_time_zone": "Europe/Moscow",
        "destination_airport_name": "Sheremetyevo International Airport",
        "destination_city_code": "MOW",
        "destination_coordinates": {
            "lat": 55.966324,
            "lon": 37.416573
        },
        "destination_time_zone": "Europe/Moscow"
    },
    {
        "depart_date": "2024-12-17T03:35:00+03:00",
        "origin": "SKX",
        "destination": "MOW",
        "gate": "OneTwoTrip",
        "return_date": "",
        "found_at": "2024-11-22T07:53:04Z",
        "trip_class": 0,
        "value": 11861,
        "number_of_changes": 1,
        "duration": 715,
        "distance": 532,
        "show_to_affiliates": true,
        "actual": true,
        "flight_number": "6010",
        "link": "/search/SKX1712SVO1?t=SU17344065001734449400000715SKXMRVSVO_46158c9047e5c0d1f00b1fbf14ea2318_11519&search_date=22112024&expected_price_uuid=4979b8f4-94ef-4d26-9bf7-2752afb0cd02&expected_price_source=share&expected_price_currency=rub&expected_price=11861",
        "origin_airport": "SKX",
        "destination_airport": "SVO",
        "departure_at": "2024-12-17T03:35:00+03:00",
        "airline": "A4",
        "price": 11861,
        "return_transfers": 0,
        "duration_to": 355,
        "duration_back": 0,
        "transfers": 1,
        "origin_airport_name": "Saransk Airport",
        "origin_city_code": "SKX",
        "origin_coordinates": {
            "lat": 54.166668,
            "lon": 45.166668
        },
        "origin_time_zone": "Europe/Moscow",
        "destination_airport_name": "Sheremetyevo International Airport",
        "destination_city_code": "MOW",
        "destination_coordinates": {
            "lat": 55.966324,
            "lon": 37.416573
        },
        "destination_time_zone": "Europe/Moscow"
    },
    {
        "depart_date": "2024-12-24T03:35:00+03:00",
        "origin": "SKX",
        "destination": "MOW",
        "gate": "Kupi.com",
        "return_date": "",
        "found_at": "2024-11-25T17:59:07Z",
        "trip_class": 0,
        "value": 12086,
        "number_of_changes": 1,
        "duration": 3680,
        "distance": 532,
        "show_to_affiliates": true,
        "actual": true,
        "flight_number": "6010",
        "link": "/search/SKX2412SVO1?t=N417350113001735232100003680SKXMRVSVO_7fcc6366125fa8715a7d5aaf0387f5d1_12087&search_date=25112024&expected_price_uuid=5f7979f7-cfb7-443c-91bf-d0433ced9803&expected_price_source=share&expected_price_currency=rub&expected_price=12086",
        "origin_airport": "SKX",
        "destination_airport": "SVO",
        "departure_at": "2024-12-24T03:35:00+03:00",
        "airline": "A4",
        "price": 12086,
        "return_transfers": 0,
        "duration_to": 370,
        "duration_back": 0,
        "transfers": 1,
        "origin_airport_name": "Saransk Airport",
        "origin_city_code": "SKX",
        "origin_coordinates": {
            "lat": 54.166668,
            "lon": 45.166668
        },
        "origin_time_zone": "Europe/Moscow",
        "destination_airport_name": "Sheremetyevo International Airport",
        "destination_city_code": "MOW",
        "destination_coordinates": {
            "lat": 55.966324,
            "lon": 37.416573
        },
        "destination_time_zone": "Europe/Moscow"
    }
]